wpe/__init__.py
wpe/wpe.py
wpe_gpu-0.1.0.dist-info/LICENSE
wpe_gpu-0.1.0.dist-info/METADATA
wpe_gpu-0.1.0.dist-info/WHEEL
wpe_gpu-0.1.0.dist-info/top_level.txt
wpe_gpu-0.1.0.dist-info/RECORD
