Metadata-Version: 2.1
Name: wpe-gpu
Version: 0.1.0
Summary: GPU-accelerated Nara WPE in CuPy
Home-page: https://github.com/desh2608/wpe
Author: Desh Raj
Author-email: r.desh26@gmail.com
License: UNKNOWN
Keywords: speech enhancement gss
Platform: UNKNOWN
License-File: LICENSE
